feather_test/__init__.py
feather_test/cli.py
feather_test/event_driven_test_result.py
feather_test/event_driven_unittest.py
feather_test/events.py
feather_test/reporters/__init__.py
feather_test/reporters/base_reporter.py
feather_test/reporters/console_reporter.py
feather_test/reporters/default_reporter.py
feather_test/reporters/html_reporter.py
feather_test/reporters/json_reporter.py
feather_test/reporters/reporter_proxy.py
feather_test/test_servers/__init__.py
feather_test/test_servers/test_server.py
feather_test/utils/__init__.py
feather_test/utils/reporter_loader.py
feather_test/utils/string_utils.py
feather_test-0.1.4.dist-info/LICENSE
feather_test-0.1.4.dist-info/METADATA
feather_test-0.1.4.dist-info/WHEEL
feather_test-0.1.4.dist-info/entry_points.txt
feather_test-0.1.4.dist-info/RECORD
