Metadata-Version: 2.1
Name: feather-test
Version: 0.1.4
Summary: Feather-test: A event-driven testing framework for Python
Home-page: https://github.com/fictitiouswizard/feather-test
License: MIT
Keywords: testing,unittest,event-driven
Author: Jason Sanders
Author-email: me@fictitiouswizard.com
Requires-Python: >=3.8,<4.0
Classifier: Development Status :: 3 - Alpha
Classifier: Intended Audience :: Developers
Classifier: License :: OSI Approved :: MIT License
Classifier: Programming Language :: Python :: 3
Classifier: Programming Language :: Python :: 3.8
Classifier: Programming Language :: Python :: 3.9
Classifier: Programming Language :: Python :: 3.10
Classifier: Programming Language :: Python :: 3.11
Classifier: Programming Language :: Python :: 3.12
Requires-Dist: colorama (>=0.4.6,<0.5.0)
Project-URL: Bug Tracker, https://github.com/fictitiouswizard/feather-test/issues
Project-URL: Documentation, https://feather-test.readthedocs.io
Project-URL: Repository, https://github.com/fictitiouswizard/feather-test
